racfu/__init__.py
racfu/racfu.py
racfu-0.0.2.dist-info/LICENSE
racfu-0.0.2.dist-info/METADATA
racfu-0.0.2.dist-info/WHEEL
racfu-0.0.2.dist-info/top_level.txt
racfu-0.0.2.dist-info/RECORD
